chess_heatmap/__init__.py
chess_heatmap/chess_dask_cluster.py
chess_heatmap/chess_image_generator.py
chess_heatmap/chess_util.py
tests/__init__.py
tests/mock_animate.py
tests/mock_axis.py
tests/mock_client.py
tests/mock_future.py
tests/mock_game.py
tests/mock_snsheatmap.py
tests/mock_subplots.py
tests/test_chess_attackers.py
tests/test_chess_dask_cluster.py
tests/test_chess_image_generator.py
tests/test_chess_util.py
tests/test_heatmap.py
chess_heatmap-0.0.6.3.dist-info/LICENSE
chess_heatmap-0.0.6.3.dist-info/METADATA
chess_heatmap-0.0.6.3.dist-info/WHEEL
chess_heatmap-0.0.6.3.dist-info/top_level.txt
chess_heatmap-0.0.6.3.dist-info/RECORD
