Metadata-Version: 2.1
Name: chess-heatmap
Version: 0.0.6.3
Summary: Package to generate chess heatmaps from pgn files
Home-page: UNKNOWN
Author: Sravanti Tatiraju
Author-email: sravanti.p21@gmail.com
License: UNKNOWN
Platform: UNKNOWN
Classifier: Programming Language :: Python :: 3
Classifier: License :: OSI Approved :: GNU General Public License (GPL)
Classifier: Operating System :: OS Independent
Requires-Python: >=3.6
